Metadata-Version: 1.1
Name: impulsare-job
Version: 1.0a1
Summary: A job reader / writer to define mappings for impulsare.
Home-page: https://github.com/impulsare/job
Author: Emmanuel Dyan
Author-email: emmanuel@impulsare.io
License: AGPLv3
Download-URL: https://github.com/impulsare/job/tarball/1.0a1
Keywords: job,python,yaml
Platform: UNKNOWN
Classifier: Development Status :: 3 - Alpha
Classifier: Intended Audience :: Developers
Classifier: Intended Audience :: Information Technology
Classifier: Intended Audience :: Science/Research
Classifier: Intended Audience :: System Administrators
Classifier: License :: OSI Approved :: GNU Affero General Public License v3 or later (AGPLv3+)
Classifier: Programming Language :: Python :: 3.3
Classifier: Programming Language :: Python :: 3.4
Classifier: Programming Language :: Python :: 3.5
Classifier: Programming Language :: Python :: 3.6
Classifier: Topic :: Scientific/Engineering
Classifier: Topic :: System :: Distributed Computing
Classifier: Topic :: System :: Systems Administration
